{
  "productos": [
    {
      "id": "1",
      "nombreProducto": "café",
      "precio": 1500,
      "categoria": "Infusiones",
      "descripcionBreve": "Una taza de café suave y aromático.",
      "descripcionAmplia": "Una taza de café suave y aromático con más detalles",
      "imagen": "url"
    },
    {
      "id": "2",
      "nombreProducto": "té",
      "precio": 1000,
      "categoria": "Infusiones",
      "descripcionBreve": "Una taza de té suave y aromático.",
      "descripcionAmplia": "Una taza de té suave y aromático con más detalles",
      "imagen": "url"
    }
  ]
}
